satrain/__init__.py
satrain/baselines.py
satrain/cli.py
satrain/config.py
satrain/data.py
satrain/definitions.py
satrain/evaluation.py
satrain/input.py
satrain/logging.py
satrain/metrics.py
satrain/plotting.py
satrain/target.py
satrain/tiling.py
satrain/utils.py
satrain/files/files_satrain.json.gz
satrain/files/files_satrain_test.json.gz
satrain/files/satrain.mplstyle
satrain/files/baselines/era5_atms_austria.nc
satrain/files/baselines/era5_atms_conus.nc
satrain/files/baselines/era5_atms_korea.nc
satrain/files/baselines/era5_gmi_austria.nc
satrain/files/baselines/era5_gmi_conus.nc
satrain/files/baselines/era5_gmi_korea.nc
satrain/files/baselines/gprof_v07_atms_austria.nc
satrain/files/baselines/gprof_v07_atms_conus.nc
satrain/files/baselines/gprof_v07_atms_korea.nc
satrain/files/baselines/gprof_v07_gmi_austria.nc
satrain/files/baselines/gprof_v07_gmi_conus.nc
satrain/files/baselines/gprof_v07_gmi_korea.nc
satrain/files/stats/ancillary.nc
satrain/files/stats/eia_atms.nc
satrain/files/stats/eia_gmi.nc
satrain/files/stats/obs_atms.nc
satrain/files/stats/obs_geo.nc
satrain/files/stats/obs_geo_ir.nc
satrain/files/stats/obs_gmi.nc
satrain/pytorch/__init__.py
satrain/pytorch/datasets.py
satrain-1.0.1.dist-info/licenses/LICENSE.txt
satrain-1.0.1.dist-info/METADATA
satrain-1.0.1.dist-info/WHEEL
satrain-1.0.1.dist-info/entry_points.txt
satrain-1.0.1.dist-info/top_level.txt
satrain-1.0.1.dist-info/RECORD
