Metadata-Version: 2.4
Name: satrain
Version: 1.0.1
Summary: A machine-learning benchmark dataset for satellite-based precipitation retrievals
Author-email: Simon Pfreundschuh <simon.pfreundschuh@colostate.edu>
Maintainer-email: Simon Pfreundschuh <simon.pfreundschuh@colostate.edu>
License-Expression: MIT
Project-URL: Source, https://github.com/simonpf/satrain/
Project-URL: Docs, https://satrain.readthedocs.io
Keywords: machine-learning,benchmark,dataset,meteorology,geophyisics
Requires-Python: >=3.10
License-File: LICENSE.txt
Requires-Dist: appdirs
Requires-Dist: click
Requires-Dist: ipywidgets
Requires-Dist: numpy<2
Requires-Dist: netCDF4<1.7
Requires-Dist: h5netcdf
Requires-Dist: hdf5plugin
Requires-Dist: jupyter-book
Requires-Dist: matplotlib
Requires-Dist: requests-cache
Requires-Dist: rich
Requires-Dist: scipy
Requires-Dist: seaborn
Requires-Dist: toml
Requires-Dist: xarray
Provides-Extra: complete
Requires-Dist: pytest; extra == "complete"
Requires-Dist: torch; extra == "complete"
Requires-Dist: torchvision; extra == "complete"
Requires-Dist: lightning; extra == "complete"
Requires-Dist: cartopy; extra == "complete"
Dynamic: license-file
